ohcrn_lei/__init__.py
ohcrn_lei/cli.py
ohcrn_lei/extractHGNCSymbols.py
ohcrn_lei/llm_calls.py
ohcrn_lei/main.py
ohcrn_lei/pdf_to_text.py
ohcrn_lei/regex_utils.py
ohcrn_lei/task.py
ohcrn_lei/task_parser.py
ohcrn_lei/trieSearch.py
ohcrn_lei/data/hgncTrie.txt
ohcrn_lei/data/molecular_test_task.txt
ohcrn_lei/data/report_task.txt
ohcrn_lei/data/variant_task.txt
ohcrn_lei-0.3.1.dist-info/METADATA
ohcrn_lei-0.3.1.dist-info/WHEEL
ohcrn_lei-0.3.1.dist-info/entry_points.txt
ohcrn_lei-0.3.1.dist-info/licenses/LICENSE
ohcrn_lei-0.3.1.dist-info/RECORD
