Metadata-Version: 2.4
Name: ohcrn-lei
Version: 0.3.1
Summary: The ohcrn-lei tool takes a PDF or TXT file of a clinical report and extracts desired information from it, which will be output in json format.
Author-email: Jochen Weile <jweile@oicr.on.ca>, Andres Melani de la Hoz <amelanidelahoz@oicr.on.ca>
License-Expression: GPL-3.0-only
License-File: LICENSE
Requires-Python: >=3.13
Requires-Dist: argparse>=1.4.0
Requires-Dist: easyocr==1.7.1
Requires-Dist: numpy>=2.2.4
Requires-Dist: openai==1.55.3
Requires-Dist: pdf2image>=1.17.0
Requires-Dist: python-dotenv==0.21.0
Requires-Dist: requests>=2.32.3
